eventsourcing_sqlalchemy/__init__.py
eventsourcing_sqlalchemy/datastore.py
eventsourcing_sqlalchemy/factory.py
eventsourcing_sqlalchemy/models.py
eventsourcing_sqlalchemy/py.typed
eventsourcing_sqlalchemy/recorders.py
eventsourcing_sqlalchemy-0.12.dist-info/LICENSE
eventsourcing_sqlalchemy-0.12.dist-info/METADATA
eventsourcing_sqlalchemy-0.12.dist-info/WHEEL
eventsourcing_sqlalchemy-0.12.dist-info/RECORD
