Metadata-Version: 2.3
Name: eventsourcing-sqlalchemy
Version: 0.12
Summary: Python package for eventsourcing with SQLAlchemy.
License: BSD 3-Clause
Author: John Bywater
Author-email: john.bywater@appropriatesoftware.net
Requires-Python: >=3.9.2,<4.0.0
Classifier: Development Status :: 4 - Beta
Classifier: License :: OSI Approved :: BSD License
Classifier: License :: Other/Proprietary License
Classifier: Programming Language :: Python
Classifier: Programming Language :: Python :: 3
Classifier: Programming Language :: Python :: 3.10
Classifier: Programming Language :: Python :: 3.11
Classifier: Programming Language :: Python :: 3.12
Classifier: Programming Language :: Python :: 3.13
Classifier: Programming Language :: Python :: 3.9
Requires-Dist: SQLAlchemy-Utils (>=0.38.2)
Requires-Dist: eventsourcing (>=9.4.6,<10.0.0)
Requires-Dist: sqlalchemy (>=1.4.26,<2.1)
Project-URL: Homepage, https://eventsourcing.readthedocs.io/
Project-URL: Repository, https://github.com/pyeventsourcing/eventsourcing-sqlalchemy
